{
  "weekdays": {"journeys":[[{"stop":"Belfast, Queen Street","time":"1750"},{"stop":"Falls Road, Royal Hospitals","time":"1757"},{"stop":"Falls Road, City Cemetery","time":"1802"},{"stop":"Kennedy Cen, Falls Road","time":"1805"},{"stop":"Andersonstown, Slievegallion\nDrive","time":"1809"},{"stop":"Stewartstown Rd, Suffolk\nLibrary","time":"1813"},{"stop":"Stewartstown Rd, Woodbourne","time":"1814"},{"stop":"Suffolk Road, Glengoland\nRoundabout","time":"1816"},{"stop":"Upper Dunmurry Road, Cherry\nRoad","time":"1818"},{"stop":"Twinbrook Est, Stewartstown\nRd","time":"1822"},{"stop":"Lagmore, Lagmore Dale","time":"1823"},{"stop":"Lagmore, Mount Eagles","time":"1833"}],[{"stop":"Belfast, Queen Street","time":"1820"},{"stop":"Falls Road, Royal Hospitals","time":"1827"},{"stop":"Falls Road, City Cemetery","time":"1832"},{"stop":"Kennedy Cen, Falls Road","time":"1835"},{"stop":"Andersonstown, Slievegallion\nDrive","time":"1839"},{"stop":"Stewartstown Rd, Suffolk\nLibrary","time":"1842"},{"stop":"Stewartstown Rd, Woodbourne","time":"1843"},{"stop":"Suffolk Road, Glengoland\nRoundabout","time":"1845"},{"stop":"Upper Dunmurry Road, Cherry\nRoad","time":"1847"},{"stop":"Twinbrook Est, Stewartstown\nRd","time":"1851"},{"stop":"Lagmore, Lagmore Dale","time":"1852"},{"stop":"Lagmore, Mount Eagles","time":"1901"}],[{"stop":"Belfast, Queen Street","time":"1915"},{"stop":"Falls Road, Royal Hospitals","time":"1920"},{"stop":"Falls Road, City Cemetery","time":"1924"},{"stop":"Kennedy Cen, Falls Road","time":"1927"},{"stop":"Andersonstown, Slievegallion\nDrive","time":"1931"},{"stop":"Stewartstown Rd, Suffolk\nLibrary","time":"1934"},{"stop":"Stewartstown Rd, Woodbourne","time":"1935"},{"stop":"Suffolk Road, Glengoland\nRoundabout","time":"1937"},{"stop":"Upper Dunmurry Road, Cherry\nRoad","time":"1939"},{"stop":"Twinbrook Est, Stewartstown\nRd","time":"1943"},{"stop":"Lagmore, Lagmore Dale","time":"1944"},{"stop":"Lagmore, Mount Eagles","time":"1953"}],[{"stop":"Belfast, Queen Street","time":"2015"},{"stop":"Falls Road, Royal Hospitals","time":"2020"},{"stop":"Falls Road, City Cemetery","time":"2024"},{"stop":"Kennedy Cen, Falls Road","time":"2027"},{"stop":"Andersonstown, Slievegallion\nDrive","time":"2031"},{"stop":"Stewartstown Rd, Suffolk\nLibrary","time":"2033"},{"stop":"Stewartstown Rd, Woodbourne","time":"2034"},{"stop":"Suffolk Road, Glengoland\nRoundabout","time":"2035"},{"stop":"Upper Dunmurry Road, Cherry\nRoad","time":"2037"},{"stop":"Twinbrook Est, Stewartstown\nRd","time":"2039"},{"stop":"Lagmore, Lagmore Dale","time":"2040"},{"stop":"Lagmore, Mount Eagles","time":"2047"}],[{"stop":"Belfast, Queen Street","time":"2115"},{"stop":"Falls Road, Royal Hospitals","time":"2118"},{"stop":"Falls Road, City Cemetery","time":"2122"},{"stop":"Kennedy Cen, Falls Road","time":"2124"},{"stop":"Andersonstown, Slievegallion\nDrive","time":"2127"},{"stop":"Stewartstown Rd, Suffolk\nLibrary","time":"2129"},{"stop":"Stewartstown Rd, Woodbourne","time":"2130"},{"stop":"Suffolk Road, Glengoland\nRoundabout","time":"2131"},{"stop":"Upper Dunmurry Road, Cherry\nRoad","time":"2133"},{"stop":"Twinbrook Est, Stewartstown\nRd","time":"2135"},{"stop":"Lagmore, Lagmore Dale","time":"2136"},{"stop":"Lagmore, Mount Eagles","time":"2143"}],[{"stop":"Belfast, Queen Street","time":"2230"},{"stop":"Falls Road, Royal Hospitals","time":"2233"},{"stop":"Falls Road, City Cemetery","time":"2237"},{"stop":"Kennedy Cen, Falls Road","time":"2239"},{"stop":"Andersonstown, Slievegallion\nDrive","time":"2242"},{"stop":"Stewartstown Rd, Suffolk\nLibrary","time":"2244"},{"stop":"Stewartstown Rd, Woodbourne","time":"2245"},{"stop":"Suffolk Road, Glengoland\nRoundabout","time":"2246"},{"stop":"Upper Dunmurry Road, Cherry\nRoad","time":"2248"},{"stop":"Twinbrook Est, Stewartstown\nRd","time":"2250"},{"stop":"Lagmore, Lagmore Dale","time":"2251"},{"stop":"Lagmore, Mount Eagles","time":"2258"}]],"frequency":"weekdays"},
  "sunday": {"journeys":[[{"stop":"Belfast, Queen Street","time":"1115"},{"stop":"Falls Road, Royal Hospitals","time":"1118"},{"stop":"Falls Road, City Cemetery","time":"1122"},{"stop":"Kennedy Cen, Falls Road","time":"1124"},{"stop":"Andersonstown, Slievegallion\nDrive","time":"1127"},{"stop":"Stewartstown Rd, Suffolk\nLibrary","time":"1129"},{"stop":"Stewartstown Rd, Woodbourne","time":"1130"},{"stop":"Suffolk Road, Glengoland\nRoundabout","time":"1131"},{"stop":"Upper Dunmurry Road, Cherry\nRoad","time":"1133"},{"stop":"Twinbrook Est, Stewartstown\nRd","time":"1135"},{"stop":"Lagmore, Lagmore Dale","time":"1136"},{"stop":"Lagmore, Mount Eagles","time":"1143"}],[{"stop":"Belfast, Queen Street","time":"1310"},{"stop":"Falls Road, Royal Hospitals","time":"1315"},{"stop":"Falls Road, City Cemetery","time":"1319"},{"stop":"Kennedy Cen, Falls Road","time":"1322"},{"stop":"Andersonstown, Slievegallion\nDrive","time":"1326"},{"stop":"Stewartstown Rd, Suffolk\nLibrary","time":"1329"},{"stop":"Stewartstown Rd, Woodbourne","time":"1330"},{"stop":"Suffolk Road, Glengoland\nRoundabout","time":"1332"},{"stop":"Upper Dunmurry Road, Cherry\nRoad","time":"1334"},{"stop":"Twinbrook Est, Stewartstown\nRd","time":"1338"},{"stop":"Lagmore, Lagmore Dale","time":"1339"},{"stop":"Lagmore, Mount Eagles","time":"1348"}],[{"stop":"Belfast, Queen Street","time":"1510"},{"stop":"Falls Road, Royal Hospitals","time":"1515"},{"stop":"Falls Road, City Cemetery","time":"1519"},{"stop":"Kennedy Cen, Falls Road","time":"1522"},{"stop":"Andersonstown, Slievegallion\nDrive","time":"1526"},{"stop":"Stewartstown Rd, Suffolk\nLibrary","time":"1529"},{"stop":"Stewartstown Rd, Woodbourne","time":"1530"},{"stop":"Suffolk Road, Glengoland\nRoundabout","time":"1532"},{"stop":"Upper Dunmurry Road, Cherry\nRoad","time":"1534"},{"stop":"Twinbrook Est, Stewartstown\nRd","time":"1538"},{"stop":"Lagmore, Lagmore Dale","time":"1539"},{"stop":"Lagmore, Mount Eagles","time":"1548"}],[{"stop":"Belfast, Queen Street","time":"1710"},{"stop":"Falls Road, Royal Hospitals","time":"1715"},{"stop":"Falls Road, City Cemetery","time":"1719"},{"stop":"Kennedy Cen, Falls Road","time":"1722"},{"stop":"Andersonstown, Slievegallion\nDrive","time":"1726"},{"stop":"Stewartstown Rd, Suffolk\nLibrary","time":"1729"},{"stop":"Stewartstown Rd, Woodbourne","time":"1730"},{"stop":"Suffolk Road, Glengoland\nRoundabout","time":"1732"},{"stop":"Upper Dunmurry Road, Cherry\nRoad","time":"1734"},{"stop":"Twinbrook Est, Stewartstown\nRd","time":"1738"},{"stop":"Lagmore, Lagmore Dale","time":"1739"},{"stop":"Lagmore, Mount Eagles","time":"1748"}],[{"stop":"Belfast, Queen Street","time":"1910"},{"stop":"Falls Road, Royal Hospitals","time":"1913"},{"stop":"Falls Road, City Cemetery","time":"1917"},{"stop":"Kennedy Cen, Falls Road","time":"1919"},{"stop":"Andersonstown, Slievegallion\nDrive","time":"1922"},{"stop":"Stewartstown Rd, Suffolk\nLibrary","time":"1924"},{"stop":"Stewartstown Rd, Woodbourne","time":"1925"},{"stop":"Suffolk Road, Glengoland\nRoundabout","time":"1926"},{"stop":"Upper Dunmurry Road, Cherry\nRoad","time":"1928"},{"stop":"Twinbrook Est, Stewartstown\nRd","time":"1930"},{"stop":"Lagmore, Lagmore Dale","time":"1931"},{"stop":"Lagmore, Mount Eagles","time":"1938"}]],"frequency":"sunday"},
  "saturday": {"journeys":[[{"stop":"Belfast, Queen Street","time":"2115"},{"stop":"Falls Road, Royal Hospitals","time":"2118"},{"stop":"Falls Road, City Cemetery","time":"2122"},{"stop":"Kennedy Cen, Falls Road","time":"2124"},{"stop":"Andersonstown, Slievegallion\nDrive","time":"2127"},{"stop":"Stewartstown Rd, Suffolk\nLibrary","time":"2129"},{"stop":"Stewartstown Rd, Woodbourne","time":"2130"},{"stop":"Suffolk Road, Glengoland\nRoundabout","time":"2131"},{"stop":"Upper Dunmurry Road, Cherry\nRoad","time":"2133"},{"stop":"Twinbrook Est, Stewartstown\nRd","time":"2135"},{"stop":"Lagmore, Lagmore Dale","time":"2136"},{"stop":"Lagmore, Mount Eagles","time":"2143"}],[{"stop":"Belfast, Queen Street","time":"2230"},{"stop":"Falls Road, Royal Hospitals","time":"2233"},{"stop":"Falls Road, City Cemetery","time":"2237"},{"stop":"Kennedy Cen, Falls Road","time":"2239"},{"stop":"Andersonstown, Slievegallion\nDrive","time":"2242"},{"stop":"Stewartstown Rd, Suffolk\nLibrary","time":"2244"},{"stop":"Stewartstown Rd, Woodbourne","time":"2245"},{"stop":"Suffolk Road, Glengoland\nRoundabout","time":"2246"},{"stop":"Upper Dunmurry Road, Cherry\nRoad","time":"2248"},{"stop":"Twinbrook Est, Stewartstown\nRd","time":"2250"},{"stop":"Lagmore, Lagmore Dale","time":"2251"},{"stop":"Lagmore, Mount Eagles","time":"2258"}]],"frequency":"saturday"}
}