{
  "weekdays": {"journeys":[[{"stop":"Belfast, Howard Street","time":"1810"},{"stop":"Botanic Ave, Shaftesbury Sq","time":"1814"},{"stop":"Ormeau Road, Agincourt\nAvenue","time":"1819"},{"stop":"Annadale, Wellington Square","time":"1822"},{"stop":"Forestside, Upper Galwally","time":"1827"},{"stop":"Rosetta, Knockbreda Road","time":"1829"},{"stop":"Mount Merrion, Rosetta Rd","time":"1831"},{"stop":"Mount Merrion Ave, Bell's\nBridge","time":"1834"},{"stop":"Montgomery Rd, Stirling Ave","time":"1836"},{"stop":"Castlereagh Rd, Clonduff","time":"1838"},{"stop":"Whincroft Road, Bus stop","time":"1840"},{"stop":"Braniel, Farmhurst Green","time":"1843"},{"stop":"Kings Road, Barnetts Rd","time":"1847"},{"stop":"Old Holywood Road,\nKennelbridge","time":"1852"},{"stop":"Holywood Rd, Knocknagoney\nAve","time":"1854"},{"stop":"Holywood Exchange,\nSainsburys","time":"1859"},{"stop":"Holywood Exchange, Ikea","time":"1901"}],[{"stop":"Belfast, Howard Street","time":"1910"},{"stop":"Botanic Ave, Shaftesbury Sq","time":"1913"},{"stop":"Ormeau Road, Agincourt\nAvenue","time":"1917"},{"stop":"Annadale, Wellington Square","time":"1920"},{"stop":"Forestside, Upper Galwally","time":"1925"},{"stop":"Rosetta, Knockbreda Road","time":"1927"},{"stop":"Mount Merrion, Rosetta Rd","time":"1929"},{"stop":"Mount Merrion Ave, Bell's\nBridge","time":"1932"},{"stop":"Montgomery Rd, Stirling Ave","time":"1934"},{"stop":"Castlereagh Rd, Clonduff","time":"1936"},{"stop":"Whincroft Road, Bus stop","time":"1938"},{"stop":"Braniel, Farmhurst Green","time":"1941"},{"stop":"Kings Road, Barnetts Rd","time":"1945"},{"stop":"Old Holywood Road,\nKennelbridge","time":"1950"},{"stop":"Holywood Rd, Knocknagoney\nAve","time":"1952"},{"stop":"Holywood Exchange,\nSainsburys","time":"1957"},{"stop":"Holywood Exchange, Ikea","time":"1959"}],[{"stop":"Belfast, Howard Street","time":"2010"},{"stop":"Botanic Ave, Shaftesbury Sq","time":"2013"},{"stop":"Ormeau Road, Agincourt\nAvenue","time":"2017"},{"stop":"Annadale, Wellington Square","time":"2020"},{"stop":"Forestside, Upper Galwally","time":"2025"},{"stop":"Rosetta, Knockbreda Road","time":"2027"},{"stop":"Mount Merrion, Rosetta Rd","time":"2029"},{"stop":"Mount Merrion Ave, Bell's\nBridge","time":"2032"},{"stop":"Montgomery Rd, Stirling Ave","time":"2033"},{"stop":"Castlereagh Rd, Clonduff","time":"2035"},{"stop":"Whincroft Road, Bus stop","time":"2036"},{"stop":"Braniel, Farmhurst Green","time":"2039"},{"stop":"Kings Road, Barnetts Rd","time":"2043"},{"stop":"Old Holywood Road,\nKennelbridge","time":"2048"},{"stop":"Holywood Rd, Knocknagoney\nAve","time":"2050"},{"stop":"Holywood Exchange,\nSainsburys","time":"2055"},{"stop":"Holywood Exchange, Ikea","time":"2057"}]],"frequency":"weekdays"},
  "sunday": null,
  "saturday": {"journeys":[[{"stop":"Belfast, Howard Street","time":"1810"},{"stop":"Botanic Ave, Shaftesbury Sq","time":"1814"},{"stop":"Ormeau Road, Agincourt\nAvenue","time":"1819"},{"stop":"Annadale, Wellington Square","time":"1822"},{"stop":"Forestside, Upper Galwally","time":"1827"},{"stop":"Rosetta, Knockbreda Road","time":"1829"},{"stop":"Mount Merrion, Rosetta Rd","time":"1831"},{"stop":"Mount Merrion Ave, Bell's\nBridge","time":"1834"},{"stop":"Montgomery Rd, Stirling Ave","time":"1836"},{"stop":"Castlereagh Rd, Clonduff","time":"1838"},{"stop":"Whincroft Road, Bus stop","time":"1840"},{"stop":"Braniel, Farmhurst Green","time":"1843"},{"stop":"Kings Road, Barnetts Rd","time":"1847"},{"stop":"Old Holywood Road,\nKennelbridge","time":"1852"},{"stop":"Holywood Rd, Knocknagoney\nAve","time":"1854"},{"stop":"Holywood Exchange,\nSainsburys","time":"1859"},{"stop":"Holywood Exchange, Ikea","time":"1901"}],[{"stop":"Belfast, Howard Street","time":"1910"},{"stop":"Botanic Ave, Shaftesbury Sq","time":"1913"},{"stop":"Ormeau Road, Agincourt\nAvenue","time":"1917"},{"stop":"Annadale, Wellington Square","time":"1920"},{"stop":"Forestside, Upper Galwally","time":"1925"},{"stop":"Rosetta, Knockbreda Road","time":"1927"},{"stop":"Mount Merrion, Rosetta Rd","time":"1929"},{"stop":"Mount Merrion Ave, Bell's\nBridge","time":"1932"},{"stop":"Montgomery Rd, Stirling Ave","time":"1934"},{"stop":"Castlereagh Rd, Clonduff","time":"1936"},{"stop":"Whincroft Road, Bus stop","time":"1938"},{"stop":"Braniel, Farmhurst Green","time":"1941"},{"stop":"Kings Road, Barnetts Rd","time":"1945"},{"stop":"Old Holywood Road,\nKennelbridge","time":"1950"},{"stop":"Holywood Rd, Knocknagoney\nAve","time":"1952"},{"stop":"Holywood Exchange,\nSainsburys","time":"1957"},{"stop":"Holywood Exchange, Ikea","time":"1959"}],[{"stop":"Belfast, Howard Street","time":"2010"},{"stop":"Botanic Ave, Shaftesbury Sq","time":"2013"},{"stop":"Ormeau Road, Agincourt\nAvenue","time":"2017"},{"stop":"Annadale, Wellington Square","time":"2020"},{"stop":"Forestside, Upper Galwally","time":"2025"},{"stop":"Rosetta, Knockbreda Road","time":"2027"},{"stop":"Mount Merrion, Rosetta Rd","time":"2029"},{"stop":"Mount Merrion Ave, Bell's\nBridge","time":"2032"},{"stop":"Montgomery Rd, Stirling Ave","time":"2033"},{"stop":"Castlereagh Rd, Clonduff","time":"2035"},{"stop":"Whincroft Road, Bus stop","time":"2036"},{"stop":"Braniel, Farmhurst Green","time":"2039"},{"stop":"Kings Road, Barnetts Rd","time":"2043"},{"stop":"Old Holywood Road,\nKennelbridge","time":"2048"},{"stop":"Holywood Rd, Knocknagoney\nAve","time":"2050"},{"stop":"Holywood Exchange,\nSainsburys","time":"2055"},{"stop":"Holywood Exchange, Ikea","time":"2057"}]],"frequency":"saturday"}
}