{
  "weekdays": {"journeys":[[{"stop":"Belfast, Wellington Place","time":"1743"},{"stop":"Carlisle Circus, Mater\nHospital","time":"1754"},{"stop":"Crumlin Rd, Agnes Street","time":"1755"},{"stop":"Ardoyne, Shops","time":"1759"},{"stop":"Crumlin Rd, Glenbank Corner","time":"1803"},{"stop":"Ligoniel, Wolfhill","time":"1808"},{"stop":"Ligoniel, Mountainhill","time":"1811"}],[{"stop":"Belfast, Wellington Place","time":"1758"},{"stop":"Carlisle Circus, Mater\nHospital","time":"1809"},{"stop":"Crumlin Rd, Agnes Street","time":"1810"},{"stop":"Ardoyne, Shops","time":"1814"},{"stop":"Crumlin Rd, Glenbank Corner","time":"1817"},{"stop":"Ligoniel, Wolfhill","time":"1821"},{"stop":"Ligoniel, Mountainhill","time":"1823"}],[{"stop":"Belfast, Wellington Place","time":"1820"},{"stop":"Carlisle Circus, Mater\nHospital","time":"1829"},{"stop":"Crumlin Rd, Agnes Street","time":"1830"},{"stop":"Ardoyne, Shops","time":"1833"},{"stop":"Crumlin Rd, Glenbank Corner","time":"1836"},{"stop":"Ligoniel, Wolfhill","time":"1840"},{"stop":"Ligoniel, Mountainhill","time":"1842"}]],"frequency":"weekdays"},
  "sunday": null,
  "saturday": {"journeys":[[{"stop":"Belfast, Wellington Place","time":"1614"},{"stop":"Carlisle Circus, Mater\nHospital","time":"1625"},{"stop":"Crumlin Rd, Agnes Street","time":"1626"},{"stop":"Ardoyne, Shops","time":"1630"},{"stop":"Crumlin Rd, Glenbank Corner","time":"1634"},{"stop":"Ligoniel, Wolfhill","time":"1639"},{"stop":"Ligoniel, Mountainhill","time":"1642"}],[{"stop":"Belfast, Wellington Place","time":"1634"},{"stop":"Carlisle Circus, Mater\nHospital","time":"1645"},{"stop":"Crumlin Rd, Agnes Street","time":"1646"},{"stop":"Ardoyne, Shops","time":"1650"},{"stop":"Crumlin Rd, Glenbank Corner","time":"1654"},{"stop":"Ligoniel, Wolfhill","time":"1659"},{"stop":"Ligoniel, Mountainhill","time":"1702"}],[{"stop":"Belfast, Wellington Place","time":"1654"},{"stop":"Carlisle Circus, Mater\nHospital","time":"1705"},{"stop":"Crumlin Rd, Agnes Street","time":"1706"},{"stop":"Ardoyne, Shops","time":"1710"},{"stop":"Crumlin Rd, Glenbank Corner","time":"1714"},{"stop":"Ligoniel, Wolfhill","time":"1719"},{"stop":"Ligoniel, Mountainhill","time":"1722"}],[{"stop":"Belfast, Wellington Place","time":"1714"},{"stop":"Carlisle Circus, Mater\nHospital","time":"1725"},{"stop":"Crumlin Rd, Agnes Street","time":"1726"},{"stop":"Ardoyne, Shops","time":"1730"},{"stop":"Crumlin Rd, Glenbank Corner","time":"1734"},{"stop":"Ligoniel, Wolfhill","time":"1739"},{"stop":"Ligoniel, Mountainhill","time":"1742"}],[{"stop":"Belfast, Wellington Place","time":"1734"},{"stop":"Carlisle Circus, Mater\nHospital","time":"1745"},{"stop":"Crumlin Rd, Agnes Street","time":"1746"},{"stop":"Ardoyne, Shops","time":"1750"},{"stop":"Crumlin Rd, Glenbank Corner","time":"1754"},{"stop":"Ligoniel, Wolfhill","time":"1759"},{"stop":"Ligoniel, Mountainhill","time":"1802"}],[{"stop":"Belfast, Wellington Place","time":"1754"},{"stop":"Carlisle Circus, Mater\nHospital","time":"1805"},{"stop":"Crumlin Rd, Agnes Street","time":"1806"},{"stop":"Ardoyne, Shops","time":"1810"},{"stop":"Crumlin Rd, Glenbank Corner","time":"1814"},{"stop":"Ligoniel, Wolfhill","time":"1819"},{"stop":"Ligoniel, Mountainhill","time":"1821"}],[{"stop":"Belfast, Wellington Place","time":"1820"},{"stop":"Carlisle Circus, Mater\nHospital","time":"1829"},{"stop":"Crumlin Rd, Agnes Street","time":"1830"},{"stop":"Ardoyne, Shops","time":"1833"},{"stop":"Crumlin Rd, Glenbank Corner","time":"1836"},{"stop":"Ligoniel, Wolfhill","time":"1840"},{"stop":"Ligoniel, Mountainhill","time":"1842"}]],"frequency":"saturday"}
}