{
  "weekdays": {"journeys":[[{"stop":"Braniel, Farmhurst Green","time":"2200"},{"stop":"Whincroft Road, Bus stop","time":"2203"},{"stop":"Castlereagh Rd, Clonduff","time":"2206"},{"stop":"Castlereagh Rd, Ladas Drive","time":"2208"},{"stop":"Short Strand, Mountpottinger\nLink","time":"2212"},{"stop":"Belfast, City Hall","time":"2218"}],[{"stop":"Braniel, Farmhurst Green","time":"2230"},{"stop":"Whincroft Road, Bus stop","time":"2233"},{"stop":"Castlereagh Rd, Clonduff","time":"2236"},{"stop":"Castlereagh Rd, Ladas Drive","time":"2238"},{"stop":"Short Strand, Mountpottinger\nLink","time":"2242"},{"stop":"Belfast, City Hall","time":"2248"}],[{"stop":"Braniel, Farmhurst Green","time":"2320"},{"stop":"Whincroft Road, Bus stop","time":"2323"},{"stop":"Castlereagh Rd, Clonduff","time":"2326"},{"stop":"Castlereagh Rd, Ladas Drive","time":"2328"},{"stop":"Short Strand, Mountpottinger\nLink","time":"2332"},{"stop":"Belfast, City Hall","time":"..."}]],"frequency":"weekdays"},
  "sunday": {"journeys":[[{"stop":"Braniel, Farmhurst Green","time":"1845"},{"stop":"Whincroft Road, Bus stop","time":"1848"},{"stop":"Castlereagh Rd, Clonduff","time":"1851"},{"stop":"Castlereagh Rd, Ladas Drive","time":"1853"},{"stop":"Short Strand, Mountpottinger\nLink","time":"1857"},{"stop":"Belfast, City Hall","time":"1903"}],[{"stop":"Braniel, Farmhurst Green","time":"1930"},{"stop":"Whincroft Road, Bus stop","time":"1933"},{"stop":"Castlereagh Rd, Clonduff","time":"1936"},{"stop":"Castlereagh Rd, Ladas Drive","time":"1938"},{"stop":"Short Strand, Mountpottinger\nLink","time":"1942"},{"stop":"Belfast, City Hall","time":"1948"}],[{"stop":"Braniel, Farmhurst Green","time":"2030"},{"stop":"Whincroft Road, Bus stop","time":"2033"},{"stop":"Castlereagh Rd, Clonduff","time":"2036"},{"stop":"Castlereagh Rd, Ladas Drive","time":"2038"},{"stop":"Short Strand, Mountpottinger\nLink","time":"2042"},{"stop":"Belfast, City Hall","time":"2048"}],[{"stop":"Braniel, Farmhurst Green","time":"2130"},{"stop":"Whincroft Road, Bus stop","time":"2133"},{"stop":"Castlereagh Rd, Clonduff","time":"2136"},{"stop":"Castlereagh Rd, Ladas Drive","time":"2138"},{"stop":"Short Strand, Mountpottinger\nLink","time":"2142"},{"stop":"Belfast, City Hall","time":"2148"}],[{"stop":"Braniel, Farmhurst Green","time":"2220"},{"stop":"Whincroft Road, Bus stop","time":"2223"},{"stop":"Castlereagh Rd, Clonduff","time":"2226"},{"stop":"Castlereagh Rd, Ladas Drive","time":"2228"},{"stop":"Short Strand, Mountpottinger\nLink","time":"2232"},{"stop":"Belfast, City Hall","time":"..."}]],"frequency":"sunday"},
  "saturday": {"journeys":[[{"stop":"Braniel, Farmhurst Green","time":"2130"},{"stop":"Whincroft Road, Bus stop","time":"2133"},{"stop":"Castlereagh Rd, Clonduff","time":"2136"},{"stop":"Castlereagh Rd, Ladas Drive","time":"2138"},{"stop":"Short Strand, Mountpottinger\nLink","time":"2142"},{"stop":"Belfast, City Hall","time":"2148"}],[{"stop":"Braniel, Farmhurst Green","time":"2200"},{"stop":"Whincroft Road, Bus stop","time":"2203"},{"stop":"Castlereagh Rd, Clonduff","time":"2206"},{"stop":"Castlereagh Rd, Ladas Drive","time":"2208"},{"stop":"Short Strand, Mountpottinger\nLink","time":"2212"},{"stop":"Belfast, City Hall","time":"2218"}],[{"stop":"Braniel, Farmhurst Green","time":"2230"},{"stop":"Whincroft Road, Bus stop","time":"2233"},{"stop":"Castlereagh Rd, Clonduff","time":"2236"},{"stop":"Castlereagh Rd, Ladas Drive","time":"2238"},{"stop":"Short Strand, Mountpottinger\nLink","time":"2242"},{"stop":"Belfast, City Hall","time":"2248"}],[{"stop":"Braniel, Farmhurst Green","time":"2320"},{"stop":"Whincroft Road, Bus stop","time":"2323"},{"stop":"Castlereagh Rd, Clonduff","time":"2326"},{"stop":"Castlereagh Rd, Ladas Drive","time":"2328"},{"stop":"Short Strand, Mountpottinger\nLink","time":"2332"},{"stop":"Belfast, City Hall","time":"..."}]],"frequency":"saturday"}
}