[null,{"journeys":[[{"stop":"Belfast, Howard Street","time":"0900"},{"stop":"Botanic Ave, Shaftesbury Sq","time":"0903"},{"stop":"Ormeau Road, Agincourt\nAvenue","time":"0906"},{"stop":"Rosetta, Knockbreda Road","time":"0910"},{"stop":"Mount Merrion, Rosetta Rd","time":"0912"},{"stop":"Rosetta, St John's Church","time":"0914"},{"stop":"Forestside, Saintfield Rd","time":"0916"},{"stop":"Saintfield Rd, Mount Oriel","time":"0918"},{"stop":"Newton Park, Colby Park","time":"0919"},{"stop":"Four Winds, Ballymaconaghy\nRd","time":"0920"},{"stop":"Laurelgrove, Ballymaconaghy\nRoad","time":"0922"}],[{"stop":"Belfast, Howard Street","time":"1100"},{"stop":"Botanic Ave, Shaftesbury Sq","time":"1103"},{"stop":"Ormeau Road, Agincourt\nAvenue","time":"1106"},{"stop":"Rosetta, Knockbreda Road","time":"1110"},{"stop":"Mount Merrion, Rosetta Rd","time":"1112"},{"stop":"Rosetta, St John's Church","time":"1114"},{"stop":"Forestside, Saintfield Rd","time":"1116"},{"stop":"Saintfield Rd, Mount Oriel","time":"1118"},{"stop":"Newton Park, Colby Park","time":"1119"},{"stop":"Four Winds, Ballymaconaghy\nRd","time":"1120"},{"stop":"Laurelgrove, Ballymaconaghy\nRoad","time":"1122"}],[{"stop":"Belfast, Howard Street","time":"1200"},{"stop":"Botanic Ave, Shaftesbury Sq","time":"1203"},{"stop":"Ormeau Road, Agincourt\nAvenue","time":"1207"},{"stop":"Rosetta, Knockbreda Road","time":"1212"},{"stop":"Mount Merrion, Rosetta Rd","time":"1214"},{"stop":"Rosetta, St John's Church","time":"1216"},{"stop":"Forestside, Saintfield Rd","time":"1218"},{"stop":"Saintfield Rd, Mount Oriel","time":"1220"},{"stop":"Newton Park, Colby Park","time":"1222"},{"stop":"Four Winds, Ballymaconaghy\nRd","time":"1224"},{"stop":"Laurelgrove, Ballymaconaghy\nRoad","time":"1226"}],[{"stop":"Belfast, Howard Street","time":"1300"},{"stop":"Botanic Ave, Shaftesbury Sq","time":"1303"},{"stop":"Ormeau Road, Agincourt\nAvenue","time":"1307"},{"stop":"Rosetta, Knockbreda Road","time":"1312"},{"stop":"Mount Merrion, Rosetta Rd","time":"1314"},{"stop":"Rosetta, St John's Church","time":"1316"},{"stop":"Forestside, Saintfield Rd","time":"1318"},{"stop":"Saintfield Rd, Mount Oriel","time":"1320"},{"stop":"Newton Park, Colby Park","time":"1322"},{"stop":"Four Winds, Ballymaconaghy\nRd","time":"1324"},{"stop":"Laurelgrove, Ballymaconaghy\nRoad","time":"1326"}],[{"stop":"Belfast, Howard Street","time":"1400"},{"stop":"Botanic Ave, Shaftesbury Sq","time":"1403"},{"stop":"Ormeau Road, Agincourt\nAvenue","time":"1407"},{"stop":"Rosetta, Knockbreda Road","time":"1412"},{"stop":"Mount Merrion, Rosetta Rd","time":"1414"},{"stop":"Rosetta, St John's Church","time":"1416"},{"stop":"Forestside, Saintfield Rd","time":"1418"},{"stop":"Saintfield Rd, Mount Oriel","time":"1420"},{"stop":"Newton Park, Colby Park","time":"1422"},{"stop":"Four Winds, Ballymaconaghy\nRd","time":"1424"},{"stop":"Laurelgrove, Ballymaconaghy\nRoad","time":"1426"}],[{"stop":"Belfast, Howard Street","time":"1500"},{"stop":"Botanic Ave, Shaftesbury Sq","time":"1503"},{"stop":"Ormeau Road, Agincourt\nAvenue","time":"1507"},{"stop":"Rosetta, Knockbreda Road","time":"1512"},{"stop":"Mount Merrion, Rosetta Rd","time":"1514"},{"stop":"Rosetta, St John's Church","time":"1516"},{"stop":"Forestside, Saintfield Rd","time":"1518"},{"stop":"Saintfield Rd, Mount Oriel","time":"1520"},{"stop":"Newton Park, Colby Park","time":"1522"},{"stop":"Four Winds, Ballymaconaghy\nRd","time":"1524"},{"stop":"Laurelgrove, Ballymaconaghy\nRoad","time":"1526"}]],"frequency":"sunday"},{"journeys":[[{"stop":"Belfast, Howard Street","time":"1800"},{"stop":"Botanic Ave, Shaftesbury Sq","time":"1803"},{"stop":"Ormeau Road, Agincourt\nAvenue","time":"1807"},{"stop":"Rosetta, Knockbreda Road","time":"1812"},{"stop":"Mount Merrion, Rosetta Rd","time":"1814"},{"stop":"Rosetta, St John's Church","time":"1816"},{"stop":"Forestside, Saintfield Rd","time":"1818"},{"stop":"Saintfield Rd, Mount Oriel","time":"1820"},{"stop":"Newton Park, Colby Park","time":"1822"},{"stop":"Four Winds, Ballymaconaghy\nRd","time":"1824"},{"stop":"Laurelgrove, Ballymaconaghy\nRoad","time":"1826"}]],"frequency":"sunday"},null]